{
  "updated": "2026-04-14T23:44:30Z",
  "totalFilings": 944,
  "filings7d": 17,
  "filings30d": 99,
  "filings90d": 527,
  "totalValue": 3669733051.13,
  "uniqueCompanies": 64,
  "topCompanies": [
    [
      "NVDA",
      {
        "total": 453867848.76,
        "count": 27,
        "name": "NVIDIA Corp"
      }
    ],
    [
      "AVGO",
      {
        "total": 435952390.01,
        "count": 32,
        "name": "Broadcom Inc"
      }
    ],
    [
      "PLTR",
      {
        "total": 426958849.09,
        "count": 19,
        "name": "Palantir Technologies"
      }
    ],
    [
      "GOOGL",
      {
        "total": 259120843.49999997,
        "count": 46,
        "name": "Alphabet Inc"
      }
    ],
    [
      "TMUS",
      {
        "total": 250402634.73,
        "count": 16,
        "name": "T-Mobile US"
      }
    ],
    [
      "CVX",
      {
        "total": 137180420.69,
        "count": 29,
        "name": "Chevron Corp"
      }
    ],
    [
      "NFLX",
      {
        "total": 135536798.5,
        "count": 23,
        "name": "Netflix Inc"
      }
    ],
    [
      "SNOW",
      {
        "total": 109707132.82,
        "count": 40,
        "name": "Snowflake Inc"
      }
    ],
    [
      "META",
      {
        "total": 101190841.0,
        "count": 53,
        "name": "Meta Platforms Inc"
      }
    ],
    [
      "CAT",
      {
        "total": 99484350.85000001,
        "count": 18,
        "name": "Caterpillar Inc"
      }
    ]
  ],
  "topInsiders": [
    [
      "Mark A Stevens",
      {
        "total": 303552000.0,
        "count": 1,
        "ticker": "NVDA",
        "company": "NVIDIA Corp"
      }
    ],
    [
      "Peter Thiel",
      {
        "total": 280000000.0,
        "count": 1,
        "ticker": "PLTR",
        "company": "Palantir Technologies"
      }
    ],
    [
      "Claure Mobile Llc",
      {
        "total": 219000000.0,
        "count": 1,
        "ticker": "TMUS",
        "company": "T-Mobile US"
      }
    ],
    [
      "H&Amp;S Investments I Lp",
      {
        "total": 170000150.06,
        "count": 1,
        "ticker": "AVGO",
        "company": "Broadcom Inc"
      }
    ],
    [
      "Puri Ajay K",
      {
        "total": 145439350.0,
        "count": 3,
        "ticker": "NVDA",
        "company": "NVIDIA Corp"
      }
    ],
    [
      "Reed Hastings",
      {
        "total": 112680665.3,
        "count": 3,
        "ticker": "NFLX",
        "company": "Netflix Inc"
      }
    ],
    [
      "Mdc Trust I",
      {
        "total": 106049025.2,
        "count": 2,
        "ticker": "GOOGL",
        "company": "Alphabet Inc"
      }
    ],
    [
      "Li Susan J",
      {
        "total": 83977168.0,
        "count": 3,
        "ticker": "META",
        "company": "Meta Platforms Inc"
      }
    ],
    [
      "D95Gt, Llc",
      {
        "total": 80000154.82,
        "count": 1,
        "ticker": "AVGO",
        "company": "Broadcom Inc"
      }
    ],
    [
      "Slootman Frank",
      {
        "total": 78383529.06,
        "count": 6,
        "ticker": "SNOW",
        "company": "Snowflake Inc"
      }
    ]
  ],
  "topFilings": [
    {
      "ticker": "NVDA",
      "company": "NVIDIA Corp",
      "insiderName": "Mark A Stevens",
      "shares": 1700000,
      "approxPrice": 178.56,
      "totalValue": 303552000.0,
      "fileDate": "2026-03-20",
      "relationship": "Director"
    },
    {
      "ticker": "PLTR",
      "company": "Palantir Technologies",
      "insiderName": "Peter Thiel",
      "shares": 2000000,
      "approxPrice": 140.0,
      "totalValue": 280000000.0,
      "fileDate": "2026-03-02",
      "relationship": "Officer"
    },
    {
      "ticker": "TMUS",
      "company": "T-Mobile US",
      "insiderName": "Claure Mobile Llc",
      "shares": 1000000,
      "approxPrice": 219.0,
      "totalValue": 219000000.0,
      "fileDate": "2026-02-12",
      "relationship": "Director"
    },
    {
      "ticker": "AVGO",
      "company": "Broadcom Inc",
      "insiderName": "H&Amp;S Investments I Lp",
      "shares": 531741,
      "approxPrice": 319.7,
      "totalValue": 170000150.06,
      "fileDate": "2026-03-25",
      "relationship": "Affiliate"
    },
    {
      "ticker": "AVGO",
      "company": "Broadcom Inc",
      "insiderName": "D95Gt, Llc",
      "shares": 250226,
      "approxPrice": 319.71,
      "totalValue": 80000154.82,
      "fileDate": "2026-03-25",
      "relationship": "Affiliate"
    },
    {
      "ticker": "AVGO",
      "company": "Broadcom Inc",
      "insiderName": "Samueli Foundation",
      "shares": 240095,
      "approxPrice": 319.82,
      "totalValue": 76786822.76,
      "fileDate": "2026-03-25",
      "relationship": "Affiliate"
    },
    {
      "ticker": "GOOGL",
      "company": "Alphabet Inc",
      "insiderName": "The Lawrence Page Trust",
      "shares": 225360,
      "approxPrice": 308.7,
      "totalValue": 69568632.0,
      "fileDate": "2026-03-12",
      "relationship": "Affiliate"
    },
    {
      "ticker": "COP",
      "company": "ConocoPhillips",
      "insiderName": "Lance Ryan Michael",
      "shares": 506800,
      "approxPrice": 127.26,
      "totalValue": 64493598.52,
      "fileDate": "2026-03-20",
      "relationship": "Officer"
    },
    {
      "ticker": "BLK",
      "company": "BlackRock Inc",
      "insiderName": "Goldstein Robert L.",
      "shares": 54190,
      "approxPrice": 1087.29,
      "totalValue": 58920187.96,
      "fileDate": "2026-02-10",
      "relationship": "Officer"
    },
    {
      "ticker": "COIN",
      "company": "Coinbase Global",
      "insiderName": "Alesia Haas",
      "shares": 364600,
      "approxPrice": 152.21,
      "totalValue": 55495799.51,
      "fileDate": "2026-02-06",
      "relationship": "Officer"
    },
    {
      "ticker": "NVDA",
      "company": "NVIDIA Corp",
      "insiderName": "Puri Ajay K",
      "shares": 300000,
      "approxPrice": 182.52,
      "totalValue": 54756038.0,
      "fileDate": "2026-03-10",
      "relationship": "Officer"
    },
    {
      "ticker": "NVDA",
      "company": "NVIDIA Corp",
      "insiderName": "Puri Ajay K",
      "shares": 300000,
      "approxPrice": 182.25,
      "totalValue": 54676153.0,
      "fileDate": "2026-03-18",
      "relationship": "Officer"
    },
    {
      "ticker": "PLTR",
      "company": "Palantir Technologies",
      "insiderName": "Alexander Karp",
      "shares": 403025,
      "approxPrice": 133.72,
      "totalValue": 53891858.16,
      "fileDate": "2026-02-20",
      "relationship": "Officer"
    },
    {
      "ticker": "GOOGL",
      "company": "Alphabet Inc",
      "insiderName": "Mdc Trust I",
      "shares": 172000,
      "approxPrice": 308.5,
      "totalValue": 53062223.6,
      "fileDate": "2026-02-27",
      "relationship": "Affiliate"
    },
    {
      "ticker": "GOOGL",
      "company": "Alphabet Inc",
      "insiderName": "Mdc Trust I",
      "shares": 172000,
      "approxPrice": 308.06,
      "totalValue": 52986801.6,
      "fileDate": "2026-02-27",
      "relationship": "Affiliate"
    },
    {
      "ticker": "QCOM",
      "company": "Qualcomm",
      "insiderName": "Qualcomm Inc",
      "shares": 4526715,
      "approxPrice": 10.39,
      "totalValue": 47032569.0,
      "fileDate": "2026-02-19",
      "relationship": "Holder of more than 10% of voting power"
    },
    {
      "ticker": "ABNB",
      "company": "Airbnb Inc",
      "insiderName": "Joseph Gebbia",
      "shares": 348000,
      "approxPrice": 133.23,
      "totalValue": 46364040.0,
      "fileDate": "2026-03-09",
      "relationship": "Director"
    },
    {
      "ticker": "PLTR",
      "company": "Palantir Technologies",
      "insiderName": "Stephen A Cohen",
      "shares": 327088,
      "approxPrice": 133.72,
      "totalValue": 43737684.02,
      "fileDate": "2026-02-20",
      "relationship": "Officer"
    },
    {
      "ticker": "SNOW",
      "company": "Snowflake Inc",
      "insiderName": "Slootman Frank",
      "shares": 200000,
      "approxPrice": 206.77,
      "totalValue": 41353996.03,
      "fileDate": "2026-01-20",
      "relationship": "Director"
    },
    {
      "ticker": "NFLX",
      "company": "Netflix Inc",
      "insiderName": "Reed Hastings",
      "shares": 420550,
      "approxPrice": 95.49,
      "totalValue": 40156458.15,
      "fileDate": "2026-04-01",
      "relationship": "Director"
    }
  ]
}